{"_type":"export","__export_format":4,"__export_date":"2022-04-29T15:10:40.720Z","__export_source":"insomnia.desktop.app:v2022.3.0","resources":[{"_id":"req_790d7ca0a88e4322880023ba8e112eb6","parentId":"fld_7f37df61d20848079ff8952585a03074","modified":1649629045785,"created":1649606065070,"url":"{{ _.url }}/{{ _.resource }}","name":"auth","description":"","method":"POST","body":{"mimeType":"application/json","text":"{\n\t\"email\": \"teste12@gmail.com\",\n\t\"password\": \"123456\"\n}"},"parameters":[],"headers":[{"name":"Content-Type","value":"application/json","id":"pair_fd186b1c40af486a975d1001802eb1d6"}],"authentication":{},"metaSortKey":-1649606065070,"isPrivate":false,"settingStoreCookies":true,"settingSendCookies":true,"settingDisableRenderRequestBody":false,"settingEncodeUrl":true,"settingRebuildPath":true,"settingFollowRedirects":"global","_type":"request"},{"_id":"fld_7f37df61d20848079ff8952585a03074","parentId":"wrk_ab303f0fae19495c909c227f02876fcc","modified":1649606272964,"created":1649606005486,"name":"Sessions","description":"","environment":{"resource":"authenticate"},"environmentPropertyOrder":{"&":["resource"]},"metaSortKey":-1649606005486,"_type":"request_group"},{"_id":"wrk_ab303f0fae19495c909c227f02876fcc","parentId":null,"modified":1649603416279,"created":1649603416279,"name":"New Document","description":"","scope":"design","_type":"workspace"},{"_id":"req_5a013de6043f4c9e9c161e28844c2019","parentId":"fld_ac188c2d88184fb0ba046f72eef6f8c2","modified":1650491089315,"created":1649803468349,"url":"{{ _.url }}/{{ _.resource }}/getAll/575f240c-7656-4322-81e0-c9e04349b6a7","name":"get","description":"","method":"GET","body":{},"parameters":[],"headers":[],"authentication":{"type":"bearer","token":"{% response 'body', 'req_790d7ca0a88e4322880023ba8e112eb6', 'b64::JC5kYXRhLnRva2Vu::46b', 'always', 60 %}"},"metaSortKey":-1649803468349,"isPrivate":false,"settingStoreCookies":true,"settingSendCookies":true,"settingDisableRenderRequestBody":false,"settingEncodeUrl":true,"settingRebuildPath":true,"settingFollowRedirects":"global","_type":"request"},{"_id":"fld_ac188c2d88184fb0ba046f72eef6f8c2","parentId":"wrk_ab303f0fae19495c909c227f02876fcc","modified":1650491000720,"created":1649604186716,"name":"Tasks","description":"","environment":{"resource":"tasks"},"environmentPropertyOrder":{"&":["resource"]},"metaSortKey":-1649604186716,"_type":"request_group"},{"_id":"req_cb476cf5fd814b4786f8f61ce58857a0","parentId":"fld_ac188c2d88184fb0ba046f72eef6f8c2","modified":1651173677746,"created":1650490826828,"url":"{{ _.url }}/{{ _.resource }}/update/0d7f88bd-0007-4653-90b9-5b15e5d04677","name":"update","description":"","method":"POST","body":{},"parameters":[],"headers":[],"authentication":{"type":"bearer","token":"{% response 'body', 'req_790d7ca0a88e4322880023ba8e112eb6', 'b64::JC5kYXRhLnRva2Vu::46b', 'always', 60 %}"},"metaSortKey":-1649749608896.5,"isPrivate":false,"settingStoreCookies":true,"settingSendCookies":true,"settingDisableRenderRequestBody":false,"settingEncodeUrl":true,"settingRebuildPath":true,"settingFollowRedirects":"global","_type":"request"},{"_id":"req_fde30a7f5d9e4def8bf4300090481af5","parentId":"fld_b9eb40649fba43f19e15bf16c309885b","modified":1650490983190,"created":1649695749444,"url":"{{ _.url }}/{{ _.resource }}/get/575f240c-7656-4322-81e0-c9e04349b6a7","name":"get","description":"","method":"GET","body":{},"parameters":[],"headers":[],"authentication":{"type":"bearer","token":"{% response 'body', 'req_790d7ca0a88e4322880023ba8e112eb6', 'b64::JC5kYXRhLnRva2Vu::46b', 'always', 60 %}"},"metaSortKey":-1649695749444,"isPrivate":false,"settingStoreCookies":true,"settingSendCookies":true,"settingDisableRenderRequestBody":false,"settingEncodeUrl":true,"settingRebuildPath":true,"settingFollowRedirects":"global","_type":"request"},{"_id":"fld_b9eb40649fba43f19e15bf16c309885b","parentId":"wrk_ab303f0fae19495c909c227f02876fcc","modified":1650490948279,"created":1649604181692,"name":"Projects","description":"","environment":{"resource":"projects"},"environmentPropertyOrder":{"&":["resource"]},"metaSortKey":-1649604181692,"_type":"request_group"},{"_id":"req_0ac50fd0b8b14b6bb582642edfc07de6","parentId":"fld_b9eb40649fba43f19e15bf16c309885b","modified":1649695825730,"created":1649638004549,"url":"{{ _.url }}/{{ _.resource }}/getAll","name":"getAll","description":"","method":"GET","body":{"mimeType":"application/json","text":"{\n\t\"user\" : {\"uid\": \"35eb7f71-71e6-4ac8-afa8-7aaeab8a16dd\"}\n}"},"parameters":[],"headers":[{"name":"Content-Type","value":"application/json","id":"pair_690d98305de243ecadbe656be971e861"}],"authentication":{"type":"bearer","token":"{% response 'body', 'req_790d7ca0a88e4322880023ba8e112eb6', 'b64::JC5kYXRhLnRva2Vu::46b', 'always', 60 %}"},"metaSortKey":-1649638004550,"isPrivate":false,"settingStoreCookies":true,"settingSendCookies":true,"settingDisableRenderRequestBody":false,"settingEncodeUrl":true,"settingRebuildPath":true,"settingFollowRedirects":"global","_type":"request"},{"_id":"req_5589ee0980a948b2a53d8020fe54334c","parentId":"fld_496c63087b224995802b62b9d94476f5","modified":1651173682588,"created":1649605924590,"url":"{{ _.url }}/{{ _.resource }}/get","name":"Get","description":"","method":"GET","body":{"mimeType":"application/json","text":""},"parameters":[{"id":"pair_f03b48066fd04c9b84fa5c13db07e83d","name":"email","value":"teste12@gmail.com","description":""}],"headers":[{"name":"Content-Type","value":"application/json","id":"pair_ab16f82f433647b1b08d0f323a5869b9"}],"authentication":{"type":"bearer","prefix":"Bearer","token":"{% response 'body', 'req_790d7ca0a88e4322880023ba8e112eb6', 'b64::JC5kYXRhLnRva2Vu::46b', 'always', 60 %}"},"metaSortKey":-1649605924590,"isPrivate":false,"settingStoreCookies":true,"settingSendCookies":true,"settingDisableRenderRequestBody":false,"settingEncodeUrl":true,"settingRebuildPath":true,"settingFollowRedirects":"global","_type":"request"},{"_id":"fld_496c63087b224995802b62b9d94476f5","parentId":"wrk_ab303f0fae19495c909c227f02876fcc","modified":1650490950517,"created":1649604153619,"name":"Users","description":"","environment":{"resource":"users"},"environmentPropertyOrder":{"&":["resource"]},"metaSortKey":-1649604153619,"_type":"request_group"},{"_id":"req_ca41900441604683a2350755c7b02273","parentId":"fld_496c63087b224995802b62b9d94476f5","modified":1651245007027,"created":1651173688617,"url":"{{ _.url }}/{{ _.resource }}/create","name":"Create","description":"","method":"POST","body":{"mimeType":"application/json","text":""},"parameters":[{"id":"pair_f03b48066fd04c9b84fa5c13db07e83d","name":"email","value":"teste12@gmail.com","description":""}],"headers":[{"name":"Content-Type","value":"application/json","id":"pair_ab16f82f433647b1b08d0f323a5869b9"}],"authentication":{"type":"bearer","prefix":"Bearer","token":"{% response 'body', 'req_790d7ca0a88e4322880023ba8e112eb6', 'b64::JC5kYXRhLnRva2Vu::46b', 'always', 60 %}","disabled":true},"metaSortKey":-1649605924540,"isPrivate":false,"settingStoreCookies":true,"settingSendCookies":true,"settingDisableRenderRequestBody":false,"settingEncodeUrl":true,"settingRebuildPath":true,"settingFollowRedirects":"global","_type":"request"},{"_id":"env_1fe182362b5ba78daa1c154bee4826c758558840","parentId":"wrk_ab303f0fae19495c909c227f02876fcc","modified":1649604038139,"created":1649603416302,"name":"Base Environment","data":{},"dataPropertyOrder":{},"color":null,"isPrivate":false,"metaSortKey":1649603416302,"_type":"environment"},{"_id":"jar_1fe182362b5ba78daa1c154bee4826c758558840","parentId":"wrk_ab303f0fae19495c909c227f02876fcc","modified":1649603416307,"created":1649603416307,"name":"Default Jar","cookies":[],"_type":"cookie_jar"},{"_id":"spc_9970ce502a524f96b5faa180bcb15e59","parentId":"wrk_ab303f0fae19495c909c227f02876fcc","modified":1649604033595,"created":1649603416294,"fileName":"ProjectTracker","contents":"","contentType":"yaml","_type":"api_spec"},{"_id":"uts_f44309fb7fd246e496d65e5a453f530a","parentId":"wrk_ab303f0fae19495c909c227f02876fcc","modified":1649603416316,"created":1649603416316,"name":"Example Test Suite","_type":"unit_test_suite"},{"_id":"env_13239ac969bf4edfae97d95344a9efbb","parentId":"env_1fe182362b5ba78daa1c154bee4826c758558840","modified":1651244777589,"created":1649604040498,"name":"dev","data":{"url":"http://localhost:3000/api"},"dataPropertyOrder":{"&":["url"]},"color":"#ce1c9f","isPrivate":false,"metaSortKey":1649604040498,"_type":"environment"},{"_id":"env_5b5a5ac0cde142f2b855c526e96814b0","parentId":"env_1fe182362b5ba78daa1c154bee4826c758558840","modified":1651244781551,"created":1649604046366,"name":"prd","data":{"url":"http://localhost:3031/api"},"dataPropertyOrder":{"&":["url"]},"color":"#0cd448","isPrivate":false,"metaSortKey":1649604046366,"_type":"environment"}]}